linuxcmdscan/__init__.py
linuxcmdscan/__main__.py
linuxcmdscan/cli.py
linuxcmdscan/exporters.py
linuxcmdscan/models.py
linuxcmdscan/registry.py
linuxcmdscan/scanner.py
linuxcmdscan/ui/__init__.py
linuxcmdscan/ui/app_window.py
linuxcmdscan-1.2.2.dist-info/licenses/LICENSE
linuxcmdscan-1.2.2.dist-info/METADATA
linuxcmdscan-1.2.2.dist-info/WHEEL
linuxcmdscan-1.2.2.dist-info/entry_points.txt
linuxcmdscan-1.2.2.dist-info/top_level.txt
linuxcmdscan-1.2.2.dist-info/RECORD
