Metadata-Version: 2.4
Name: linuxcmdscan
Version: 1.2.2
Summary: Inventory Linux command usage across repositories
License-Expression: MIT
Requires-Python: >=3.9
License-File: LICENSE
Dynamic: license-file
